LICENSE
MANIFEST.in
README.md
setup.py
bin/floyd
floyd/__init__.py
floyd/__main__.py
floyd/app.py
floyd/commands.py
floyd/controllers.py
floyd/main.py
floyd/options.py
floyd.egg-info/PKG-INFO
floyd.egg-info/SOURCES.txt
floyd.egg-info/dependency_links.txt
floyd.egg-info/requires.txt
floyd.egg-info/top_level.txt