Metadata-Version: 1.0
Name: floyd
Version: 0.0.3
Summary: A command line static website generator for popular cloud hosting providers
Home-page: http://github.com/nikcub/floyd
Author: Nik Cubrilovic <nikcub@gmail.com>
Author-email: nikcub@gmail.com
License: BSD
Keywords: website,appengine,s3,cms,blog
Platform: linux
Platform: osx
Platform: win32
